bshlib/__init__.py
bshlib/_version.py
bshlib/exception.py
bshlib/globals.py
bshlib/output_mgr.py
bshlib/shell_curator.py
bshlib/singleton.py
bshlib/suffix_mgr.py
bshlib/utils.py
bshlib-0.6.0.dist-info/LICENSE
bshlib-0.6.0.dist-info/METADATA
bshlib-0.6.0.dist-info/WHEEL
bshlib-0.6.0.dist-info/top_level.txt
bshlib-0.6.0.dist-info/RECORD
