Metadata-Version: 2.1
Name: bshlib
Version: 0.6.0
Summary: Bashiron's personal utilities.
Author-email: bashiron <bioshiron@gmail.com>
Project-URL: Homepage, https://github.com/bashiron/python-bshlib
Project-URL: Issues, https://github.com/bashiron/python-bshlib/issues
Keywords: utility
Classifier: Development Status :: 3 - Alpha
Classifier: License :: OSI Approved :: GNU General Public License v3 (GPLv3)
Classifier: Operating System :: POSIX :: Linux
Classifier: Programming Language :: Python :: 3.11
Classifier: Topic :: Software Development :: Libraries
Classifier: Topic :: System
Classifier: Topic :: Utilities
Requires-Python: >=3.11
License-File: LICENSE
Requires-Dist: pandas ==2.2.3
Requires-Dist: more-itertools ==10.6.0
Requires-Dist: loguru ==0.7.3
Requires-Dist: opencv-python ==4.11.0.86
